setup.py
collections/__init__.py
micropython_collections.egg-info/PKG-INFO
micropython_collections.egg-info/SOURCES.txt
micropython_collections.egg-info/dependency_links.txt
micropython_collections.egg-info/top_level.txt